tracextracturl/__init__.py
tracextracturl/extracturl.py
tracextracturl/macro.py
TracExtractUrl-0.5.dist-info/METADATA
TracExtractUrl-0.5.dist-info/WHEEL
TracExtractUrl-0.5.dist-info/entry_points.txt
TracExtractUrl-0.5.dist-info/top_level.txt
TracExtractUrl-0.5.dist-info/RECORD
