Metadata-Version: 2.1
Name: TracExtractUrl
Version: 0.5
Summary: Provides `extract_url` method to extract the URL from TracWiki links.
Home-page: https://trac-hacks.org/wiki/ExtractUrlPlugin
Author: Martin Scharrer
Author-email: martin@scharrer-online.de
License: GPLv3
Download-URL: https://pypi.python.org/pypi/TracExtractUrl
Keywords: trac plugin extract url
Platform: UNKNOWN
Classifier: Framework :: Trac
